LICENSE
MANIFEST.in
README.md
pyproject.toml
setup.cfg
setup.py
dj_rest_firebase/__init__.py
dj_rest_firebase/admin.py
dj_rest_firebase/apps.py
dj_rest_firebase/auth.py
dj_rest_firebase/endpoints.py
dj_rest_firebase/models.py
dj_rest_firebase/views.py
dj_rest_firebase.egg-info/PKG-INFO
dj_rest_firebase.egg-info/SOURCES.txt
dj_rest_firebase.egg-info/dependency_links.txt
dj_rest_firebase.egg-info/requires.txt
dj_rest_firebase.egg-info/top_level.txt
dj_rest_firebase/migrations/0001_initial.py
dj_rest_firebase/migrations/__init__.py